setup.py
ONSdatabaker/__init__.py
ONSdatabaker/bake.py
ONSdatabaker/constants.py
ONSdatabaker/json2csv.py
ONSdatabaker/overrides.py
ONSdatabaker/scan.py
ONSdatabaker/sortcsv.py
ONSdatabaker/structure_csv_default.py
ONSdatabaker/utf8csv.py
ONSdatabaker.egg-info/PKG-INFO
ONSdatabaker.egg-info/SOURCES.txt
ONSdatabaker.egg-info/dependency_links.txt
ONSdatabaker.egg-info/entry_points.txt
ONSdatabaker.egg-info/namespace_packages.txt
ONSdatabaker.egg-info/not-zip-safe
ONSdatabaker.egg-info/requires.txt
ONSdatabaker.egg-info/top_level.txt
ONSdatabaker/richxlrd/__init__.py
ONSdatabaker/richxlrd/richxlrd.py
test/test.py
test/test_fail.py