Metadata-Version: 1.1
Name: ONSdatabaker
Version: 1.1.3
Summary: Excel Output Transformation
Home-page: http://github.com/ONS-OpenData/ONSdatabaker/
Author: Office for National Statistics
Author-email: michael.adams@ons.gsi.gov.uk
License: AGPL
Platform: UNKNOWN
Classifier: Development Status :: 3 - Alpha
Classifier: Programming Language :: Python
Classifier: License :: OSI Approved :: GNU Affero General Public License v3 or later (AGPLv3+)
